idl2py/__init__.py
idl2py/idl2py.py
idl2py/data/idl2py_sed.txt
idl2py-1.0.5.data/scripts/idl2py
idl2py-1.0.5.dist-info/LICENSE
idl2py-1.0.5.dist-info/METADATA
idl2py-1.0.5.dist-info/WHEEL
idl2py-1.0.5.dist-info/top_level.txt
idl2py-1.0.5.dist-info/RECORD
