Metadata-Version: 2.1
Name: idl2py
Version: 1.0.5
Summary: Simple IDL to Python converter
Home-page: https://github.com/dnidever/idl2py
Author: David Nidever
Author-email: dnidever@montana.edu
License: MIT
Platform: UNKNOWN
Requires: numpy
Requires-Python: >=3.6
Requires-Dist: astropy
Requires-Dist: scipy
Provides-Extra: docs
Requires-Dist: sphinx (==3.0.1) ; extra == 'docs'
Requires-Dist: sphinx-astropy ; extra == 'docs'
Requires-Dist: nbsphinx ; extra == 'docs'
Requires-Dist: nbconvert ; extra == 'docs'
Requires-Dist: nbformat ; extra == 'docs'
Requires-Dist: ipykernel ; extra == 'docs'
Provides-Extra: test
Requires-Dist: pytest ; extra == 'test'
Requires-Dist: pytest-astropy ; extra == 'test'
Requires-Dist: ipython ; extra == 'test'
